dlp_data_gen/.DS_Store
dlp_data_gen/__init__.py
dlp_data_gen/openai_assistant.py
dlp_data_scraper/__init__.py
dlp_data_scraper/requirements.txt
dlp_data_scraper/umbrella.py
dlp_data_scraper-0.1.3.dist-info/LICENSE
dlp_data_scraper-0.1.3.dist-info/METADATA
dlp_data_scraper-0.1.3.dist-info/WHEEL
dlp_data_scraper-0.1.3.dist-info/RECORD
