Metadata-Version: 2.1
Name: dlp_data_scraper
Version: 0.1.3
Summary: A simple data scraper for the DLP website
Author: BenderScript
Author-email: 6779302+BenderScript@users.noreply.github.com
Requires-Python: >=3.11,<4.0
Classifier: Programming Language :: Python :: 3
Classifier: Programming Language :: Python :: 3.11
Classifier: Programming Language :: Python :: 3.12
Requires-Dist: beautifulsoup4 (>=4.12.2,<5.0.0)
Requires-Dist: bs4 (>=0.0.1,<0.0.2)
Requires-Dist: fpdf (>=1.7.2,<2.0.0)
Requires-Dist: requests (>=2.31.0,<3.0.0)
Requires-Dist: selenium (>=4.16.0,<5.0.0)
